currency_converter_and_calculator/__init__.py
currency_converter_and_calculator/main.py
currency_converter_and_calculator/assets/coin.png
currency_converter_and_calculator/assets/coin2.png
currency_converter_and_calculator-0.2.0.dist-info/licenses/LICENSE
currency_converter_and_calculator-0.2.0.dist-info/METADATA
currency_converter_and_calculator-0.2.0.dist-info/WHEEL
currency_converter_and_calculator-0.2.0.dist-info/entry_points.txt
currency_converter_and_calculator-0.2.0.dist-info/top_level.txt
currency_converter_and_calculator-0.2.0.dist-info/RECORD
