Metadata-Version: 2.4
Name: currency_converter_and_calculator
Version: 0.2.0
Summary: A currency converter and calculator
Home-page: https://github.com/bunnybunnybun/Coin-Calculator
Author: Carlisle
Classifier: Programming Language :: Python :: 3
Classifier: Operating System :: OS Independent
Requires-Python: >=3.6
License-File: LICENSE
Requires-Dist: FreeSimpleGUI>=0.6.0
Dynamic: author
Dynamic: classifier
Dynamic: description
Dynamic: description-content-type
Dynamic: home-page
Dynamic: license-file
Dynamic: requires-dist
Dynamic: requires-python
Dynamic: summary
